{"Api.tag":"null/费用报销单","getById":{},"deleteById":{"ApiOperation.value":"删除费用报销单","ApiImplicitParam.ReimbursementVOMeta.ID.name":"主键"},"save":{"ApiImplicitParam.ReimbursementVOMeta.TITLE.name":"费用名称","ApiOperation.value":"保存费用报销单","ApiImplicitParam.ReimbursementVOMeta.ID.name":"主键","ApiImplicitParam.ReimbursementVOMeta.STATUS.name":"审批状态","ApiImplicitParam.ReimbursementVOMeta.AMOUNT.name":"报销金额"},"insert":{"ApiImplicitParam.ReimbursementVOMeta.TITLE.name":"费用名称","ApiOperation.value":"添加费用报销单","ApiImplicitParam.ReimbursementVOMeta.ID.name":"主键","ApiImplicitParam.ReimbursementVOMeta.STATUS.name":"审批状态","ApiImplicitParam.ReimbursementVOMeta.AMOUNT.name":"报销金额"},"update":{"ApiImplicitParam.ReimbursementVOMeta.TITLE.name":"费用名称","ApiOperation.value":"更新费用报销单","ApiImplicitParam.ReimbursementVOMeta.ID.name":"主键","ApiImplicitParam.ReimbursementVOMeta.STATUS.name":"审批状态","ApiImplicitParam.ReimbursementVOMeta.AMOUNT.name":"报销金额"},"queryPagedList":{"ApiImplicitParam.ReimbursementVOMeta.TITLE.name":"费用名称","ApiOperation.value":"分页查询费用报销单","ApiImplicitParam.ReimbursementVOMeta.ID.name":"主键","ApiImplicitParam.ReimbursementVOMeta.STATUS.name":"审批状态","ApiImplicitParam.ReimbursementVOMeta.AMOUNT.name":"报销金额"},"queryList":{"ApiImplicitParam.ReimbursementVOMeta.TITLE.name":"费用名称","ApiOperation.value":"查询费用报销单","ApiImplicitParam.ReimbursementVOMeta.ID.name":"主键","ApiImplicitParam.ReimbursementVOMeta.STATUS.name":"审批状态","ApiImplicitParam.ReimbursementVOMeta.AMOUNT.name":"报销金额"}}